alibabacloud_imagesearch20201214/__init__.py
alibabacloud_imagesearch20201214/client.py
alibabacloud_imagesearch20201214/models/__init__.py
alibabacloud_imagesearch20201214/models/_add_image_advance_request.py
alibabacloud_imagesearch20201214/models/_add_image_request.py
alibabacloud_imagesearch20201214/models/_add_image_response.py
alibabacloud_imagesearch20201214/models/_add_image_response_body.py
alibabacloud_imagesearch20201214/models/_compare_similar_by_image_advance_request.py
alibabacloud_imagesearch20201214/models/_compare_similar_by_image_request.py
alibabacloud_imagesearch20201214/models/_compare_similar_by_image_response.py
alibabacloud_imagesearch20201214/models/_compare_similar_by_image_response_body.py
alibabacloud_imagesearch20201214/models/_delete_image_request.py
alibabacloud_imagesearch20201214/models/_delete_image_response.py
alibabacloud_imagesearch20201214/models/_delete_image_response_body.py
alibabacloud_imagesearch20201214/models/_detail_request.py
alibabacloud_imagesearch20201214/models/_detail_response.py
alibabacloud_imagesearch20201214/models/_detail_response_body.py
alibabacloud_imagesearch20201214/models/_dump_meta_list_request.py
alibabacloud_imagesearch20201214/models/_dump_meta_list_response.py
alibabacloud_imagesearch20201214/models/_dump_meta_list_response_body.py
alibabacloud_imagesearch20201214/models/_dump_meta_request.py
alibabacloud_imagesearch20201214/models/_dump_meta_response.py
alibabacloud_imagesearch20201214/models/_dump_meta_response_body.py
alibabacloud_imagesearch20201214/models/_increase_instance_request.py
alibabacloud_imagesearch20201214/models/_increase_instance_response.py
alibabacloud_imagesearch20201214/models/_increase_instance_response_body.py
alibabacloud_imagesearch20201214/models/_increase_list_request.py
alibabacloud_imagesearch20201214/models/_increase_list_response.py
alibabacloud_imagesearch20201214/models/_increase_list_response_body.py
alibabacloud_imagesearch20201214-4.2.3.dist-info/LICENSE
alibabacloud_imagesearch20201214-4.2.3.dist-info/METADATA
alibabacloud_imagesearch20201214-4.2.3.dist-info/WHEEL
alibabacloud_imagesearch20201214-4.2.3.dist-info/top_level.txt
alibabacloud_imagesearch20201214-4.2.3.dist-info/RECORD
